aeromet_py/__init__.py
aeromet_py/__main__.py
aeromet_py/__version__.py
aeromet_py/database/__init__.py
aeromet_py/database/countries.py
aeromet_py/database/stations.py
aeromet_py/reports/__init__.py
aeromet_py/reports/metar.py
aeromet_py/reports/models/__init__.py
aeromet_py/reports/models/base/__init__.py
aeromet_py/reports/models/base/change_indicator.py
aeromet_py/reports/models/base/cloud.py
aeromet_py/reports/models/base/distance.py
aeromet_py/reports/models/base/errors.py
aeromet_py/reports/models/base/flight_rules.py
aeromet_py/reports/models/base/group.py
aeromet_py/reports/models/base/modifier.py
aeromet_py/reports/models/base/numeric.py
aeromet_py/reports/models/base/pressure.py
aeromet_py/reports/models/base/report.py
aeromet_py/reports/models/base/station.py
aeromet_py/reports/models/base/string_attribute.py
aeromet_py/reports/models/base/temperature.py
aeromet_py/reports/models/base/time.py
aeromet_py/reports/models/base/type.py
aeromet_py/reports/models/base/wind.py
aeromet_py/reports/models/metar/__init__.py
aeromet_py/reports/models/metar/cloud.py
aeromet_py/reports/models/metar/pressure.py
aeromet_py/reports/models/metar/recent_weather.py
aeromet_py/reports/models/metar/runway_range.py
aeromet_py/reports/models/metar/runway_state.py
aeromet_py/reports/models/metar/sea_state.py
aeromet_py/reports/models/metar/should_be_cavok.py
aeromet_py/reports/models/metar/temperatures.py
aeromet_py/reports/models/metar/trend_indicator.py
aeromet_py/reports/models/metar/visibility.py
aeromet_py/reports/models/metar/weather.py
aeromet_py/reports/models/metar/weather_trend.py
aeromet_py/reports/models/metar/wind.py
aeromet_py/reports/models/metar/wind_variation.py
aeromet_py/reports/models/metar/windshear.py
aeromet_py/reports/models/taf/__init__.py
aeromet_py/reports/models/taf/cancelled.py
aeromet_py/reports/models/taf/change_forecast.py
aeromet_py/reports/models/taf/change_indicator.py
aeromet_py/reports/models/taf/missing.py
aeromet_py-0.1.2.dist-info/LICENSE
aeromet_py-0.1.2.dist-info/WHEEL
aeromet_py-0.1.2.dist-info/METADATA
aeromet_py-0.1.2.dist-info/RECORD
