Metadata-Version: 2.1
Name: aeromet-py
Version: 0.1.2
Summary: Python library to parse meteorological information of aeronautical stations.
Home-page: https://github.com/TAF-Verification/aeromet-py
License: MIT
Author: diego-garro
Author-email: diego.garromolina@yahoo.com
Requires-Python: >=3.7,<4.0
Classifier: License :: OSI Approved :: MIT License
Classifier: Programming Language :: Python :: 3
Classifier: Programming Language :: Python :: 3.7
Classifier: Programming Language :: Python :: 3.8
Classifier: Programming Language :: Python :: 3.9
Classifier: Programming Language :: Python :: 3.10
Requires-Dist: typing-extensions (>=4.2.0,<5.0.0)
Project-URL: Documentation, https://github.com/TAF-Verification/aeromet-py/blob/main/doc/docs.md
Project-URL: Repository, https://github.com/TAF-Verification/aeromet-py
